paddle-stubs/_C_ops.pyi
paddle-stubs/__init__.pyi
paddle-stubs/_legacy_C_ops.pyi
paddle-stubs/_typing/__init__.pyi
paddle-stubs/_typing/basic.pyi
paddle-stubs/_typing/device.pyi
paddle-stubs/_typing/dtype.pyi
paddle-stubs/_typing/layout.pyi
paddle-stubs/_typing/shape.pyi
paddle-stubs/_typing/tensor.pyi
paddle-stubs/amp/__init__.pyi
paddle-stubs/amp/auto_cast.pyi
paddle-stubs/amp/grad_scaler.pyi
paddle-stubs/autograd/__init__.pyi
paddle-stubs/autograd/backward_mode.pyi
paddle-stubs/autograd/functional.pyi
paddle-stubs/autograd/py_layer.pyi
paddle-stubs/base/__init__.pyi
paddle-stubs/base/average.pyi
paddle-stubs/base/backward.pyi
paddle-stubs/base/clip.pyi
paddle-stubs/base/communicator.pyi
paddle-stubs/base/compiler.pyi
paddle-stubs/base/contrib/__init__.pyi
paddle-stubs/base/contrib/extend_optimizer/__init__.pyi
paddle-stubs/base/contrib/extend_optimizer/extend_optimizer_with_weight_decay.pyi
paddle-stubs/base/contrib/memory_usage_calc.pyi
paddle-stubs/base/contrib/model_stat.pyi
paddle-stubs/base/contrib/op_frequence.pyi
paddle-stubs/base/contrib/optimizer.pyi
paddle-stubs/base/core.pyi
paddle-stubs/base/data.pyi
paddle-stubs/base/data_feed_desc.pyi
paddle-stubs/base/data_feeder.pyi
paddle-stubs/base/dataloader/__init__.pyi
paddle-stubs/base/dataloader/batch_sampler.pyi
paddle-stubs/base/dataloader/collate.pyi
paddle-stubs/base/dataloader/dataloader_iter.pyi
paddle-stubs/base/dataloader/dataset.pyi
paddle-stubs/base/dataloader/fetcher.pyi
paddle-stubs/base/dataloader/flat.pyi
paddle-stubs/base/dataloader/sampler.pyi
paddle-stubs/base/dataloader/worker.pyi
paddle-stubs/base/dataset.pyi
paddle-stubs/base/debugger.pyi
paddle-stubs/base/default_scope_funcs.pyi
paddle-stubs/base/device_worker.pyi
paddle-stubs/base/distribute_lookup_table.pyi
paddle-stubs/base/dygraph/__init__.pyi
paddle-stubs/base/dygraph/amp/__init__.pyi
paddle-stubs/base/dygraph/amp/auto_cast.pyi
paddle-stubs/base/dygraph/amp/loss_scaler.pyi
paddle-stubs/base/dygraph/base.pyi
paddlepaddle_stubs-3.0.0a1.dist-info/LICENSE
paddlepaddle_stubs-3.0.0a1.dist-info/METADATA
paddlepaddle_stubs-3.0.0a1.dist-info/WHEEL
paddlepaddle_stubs-3.0.0a1.dist-info/RECORD
