Metadata-Version: 2.1
Name: paddlepaddle-stubs
Version: 3.0.0a1
Summary: A stubs package as described in PEP 561 for PaddlePaddle
Home-page: https://github.com/cattidea/paddlepaddle-stubs
License: MIT
Keywords: PEP 561,PEP 484,Type Hints,PaddlePaddle
Author: Nyakku Shigure
Author-email: sigure.qaq@gmail.com
Requires-Python: >=3.8.0,<4.0.0
Classifier: License :: OSI Approved :: MIT License
Classifier: Operating System :: OS Independent
Classifier: Programming Language :: Python
Classifier: Programming Language :: Python :: 3
Classifier: Programming Language :: Python :: 3.8
Classifier: Programming Language :: Python :: 3.9
Classifier: Programming Language :: Python :: 3.10
Classifier: Programming Language :: Python :: 3.11
Classifier: Programming Language :: Python :: 3.12
Classifier: Programming Language :: Python :: Implementation :: CPython
Classifier: Typing :: Typed
Requires-Dist: typing-extensions (>=4.7.1,<5.0.0)
Project-URL: Repository, https://github.com/cattidea/paddlepaddle-stubs
